Функциональная Схемотехника/lab2_verilog/mult.v
// mult.v — последовательный умножитель "в столбик" (16×8 бит)
module mult #(parameter W1 = 16, parameter W2 = 8)(
    input clk,
    input rst,
    input start,
    input [W1-1:0] a,
    input [W2-1:0] b,
    output reg [W1+W2-1:0] y,
    output reg done
);
    reg [W1-1:0] A;
    reg [W2-1:0] B;
    reg [W1+W2-1:0] acc;
    reg [3:0] count;
    reg busy;

    always @(posedge clk or posedge rst) begin
        if (rst) begin
            y <= 0;
            acc <= 0;
            A <= 0;
            B <= 0;
            count <= 0;
            done <= 0;
            busy <= 0;
        end else begin
            done <= 0;
            if (start && !busy) begin
                A <= a;
                B <= b;
                acc <= 0;
                count <= 0;
                busy <= 1;
            end else if (busy) begin
                if (B[0])
                    acc <= acc + A;
                A <= A << 1;
                B <= B >> 1;
                count <= count + 1;

                if (count == W2-1) begin
                    y <= acc;
                    done <= 1;
                    busy <= 0;
                end
            end
        end
    end
endmodule

Функциональная Схемотехника/lab2_verilog/func.v
// func.v — модуль вычисления функции y = a*b + a^3
module func #(parameter W = 8) (
    input clk,
    input rst,
    input start,
    input [W-1:0] a,
    input [W-1:0] b,
    output reg [2*W-1:0] y,
    output reg done,
    output reg busy
);
    // --- состояния автомата ---
    localparam IDLE = 3'd0;
    localparam MUL1 = 3'd1; // a*b
    localparam MUL2 = 3'd2; // a*a
    localparam MUL3 = 3'd3; // (a^2)*a
    localparam ADD  = 3'd4; // сложение
    localparam DONE = 3'd5;

    reg [2:0] state;

    // --- сигналы к умножителю ---
    reg        start_mult;
    reg [W-1:0] opA, opB;
    wire [23:0] mult_out;      // 16×8 = 24 бита
    wire        done_mult;

    // --- промежуточные результаты ---
    reg [15:0] ab_res;         // a*b
    reg [15:0] a2_res;         // a^2
    reg [23:0] a3_res;         // a^3 (шире!)

    // --- итерационный умножитель (16×8 бит) ---
    mult #(16, 8) u_mult(
        .clk(clk),
        .rst(rst),
        .start(start_mult),
        .a({8'b0, opA}),   // расширяем opA до 16 бит
        .b(opB),
        .y(mult_out),
        .done(done_mult)
    );

    // --- автомат управления ---
    always @(posedge clk or posedge rst) begin
        if (rst) begin
            state       <= IDLE;
            done        <= 0;
            busy        <= 0;
            y           <= 0;
            ab_res      <= 0;
            a2_res      <= 0;
            a3_res      <= 0;
            start_mult  <= 0;
            opA         <= 0;
            opB         <= 0;
        end else begin
            start_mult <= 0; // по умолчанию не дёргаем
            done       <= 0;

            case (state)
                IDLE: begin
                    if (start) begin
                        busy       <= 1;
                        opA        <= a;
                        opB        <= b;
                        start_mult <= 1;   // запускаем a*b
                        state      <= MUL1;
                    end
                end

                MUL1: begin
                    if (done_mult) begin
                        ab_res     <= mult_out[15:0]; // сохраняем a*b
                        opA        <= a;
                        opB        <= a;
                        start_mult <= 1;              // запускаем a*a
                        state      <= MUL2;
                    end
                end

                MUL2: begin
                    if (done_mult) begin
                        a2_res     <= mult_out[15:0]; // сохраняем a^2 полностью
                        opA        <= mult_out[15:0]; // теперь не обрезаем!
                        opB        <= a;
                        start_mult <= 1;              // запускаем (a^2)*a
                        state      <= MUL3;
                    end
                end

                MUL3: begin
                    if (done_mult) begin
                        a3_res <= mult_out;  // сохраняем a^3 (24 бита)
                        state  <= ADD;
                    end
                end

                ADD: begin
                    y     <= ab_res + a3_res[15:0]; // складываем
                    state <= DONE;
                end

                DONE: begin
                    done  <= 1;
                    busy  <= 0;
                    state <= IDLE;
                end
            endcase
        end
    end
endmodule

Функциональная Схемотехника/lab2_verilog/func_tb.v
// func_tb.v — тестбенч для проверки работы func
`timescale 1ns/1ps

module func_tb;
    reg clk, rst, start;
    reg [7:0] a, b;
    wire [15:0] y;
    wire done, busy;

    func #(8) dut (
        .clk(clk), .rst(rst), .start(start),
        .a(a), .b(b), .y(y), .done(done), .busy(busy)
    );

    initial begin
        $dumpfile("dump.vcd");
        $dumpvars(0, func_tb);

        clk = 0;
        rst = 1;
        start = 0;
        a = 0; b = 0;
        #10 rst = 0;

        // Тест 1
        @(negedge clk);
        a = 3; b = 4;
        start = 1;
        @(negedge clk);
        start = 0;

        wait(done);
        #1 $display("a=%0d b=%0d y=%0d (ожидалось 39)", a, b, y);

        // Тест 2
        @(negedge clk);
        a = 5; b = 2;
        start = 1;
        @(negedge clk);
        start = 0;

        wait(done);
        #1 $display("a=%0d b=%0d y=%0d (ожидалось 135)", a, b, y);

        // Тест 3
        @(negedge clk);
        a = 10; b = 10;
        start = 1;
        @(negedge clk);
        start = 0;

        wait(done);
        #1 $display("a=%0d b=%0d y=%0d (ожидалось 1100)", a, b, y);

        // Дополнительные тесты
@(negedge clk); a = 0; b = 0; start = 1; @(negedge clk); start = 0; wait(done);
#1 $display("a=%0d b=%0d y=%0d (ожидалось 0)", a, b, y);

@(negedge clk); a = 1; b = 5; start = 1; @(negedge clk); start = 0; wait(done);
#1 $display("a=%0d b=%0d y=%0d (ожидалось 6)", a, b, y);

@(negedge clk); a = 2; b = 7; start = 1; @(negedge clk); start = 0; wait(done);
#1 $display("a=%0d b=%0d y=%0d (ожидалось 22)", a, b, y);

@(negedge clk); a = 4; b = 3; start = 1; @(negedge clk); start = 0; wait(done);
#1 $display("a=%0d b=%0d y=%0d (ожидалось 76)", a, b, y);

@(negedge clk); a = 8; b = 1; start = 1; @(negedge clk); start = 0; wait(done);
#1 $display("a=%0d b=%0d y=%0d (ожидалось 520)", a, b, y);

@(negedge clk); a = 10; b = 0; start = 1; @(negedge clk); start = 0; wait(done);
#1 #1$display("a=%0d b=%0d y=%0d (ожидалось 1000)", a, b, y);

@(negedge clk); a = 15; b = 15; start = 1; @(negedge clk); start = 0; wait(done);
#1 $display("a=%0d b=%0d y=%0d (ожидалось 3600)", a, b, y);

        #20 $finish;
    end

    always #5 clk = ~clk;
endmodule

Функциональная Схемотехника/lab2_verilog/dump.vcd
$date
	Tue Oct 28 16:47:50 2025
$end
$version
	Icarus Verilog
$end
$timescale
	1ps
$end
$scope module func_tb $end
$var wire 16 ! y [15:0] $end
$var wire 1 " done $end
$var wire 1 # busy $end
$var reg 8 $ a [7:0] $end
$var reg 8 % b [7:0] $end
$var reg 1 & clk $end
$var reg 1 ' rst $end
$var reg 1 ( start $end
$scope module dut $end
$var wire 8 ) a [7:0] $end
$var wire 8 * b [7:0] $end
$var wire 1 & clk $end
$var wire 1 ' rst $end
$var wire 1 ( start $end
$var wire 24 + mult_out [23:0] $end
$var wire 1 , done_mult $end
$var parameter 3 - ADD $end
$var parameter 3 . DONE $end
$var parameter 3 / IDLE $end
$var parameter 3 0 MUL1 $end
$var parameter 3 1 MUL2 $end
$var parameter 3 2 MUL3 $end
$var parameter 32 3 W $end
$var reg 16 4 a2_res [15:0] $end
$var reg 24 5 a3_res [23:0] $end
$var reg 16 6 ab_res [15:0] $end
$var reg 1 # busy $end
$var reg 1 " done $end
$var reg 8 7 opA [7:0] $end
$var reg 8 8 opB [7:0] $end
$var reg 1 9 start_mult $end
$var reg 3 : state [2:0] $end
$var reg 16 ; y [15:0] $end
$scope module u_mult $end
$var wire 16 < a [15:0] $end
$var wire 8 = b [7:0] $end
$var wire 1 & clk $end
$var wire 1 ' rst $end
$var wire 1 9 start $end
$var parameter 32 > W1 $end
$var parameter 32 ? W2 $end
$var reg 16 @ A [15:0] $end
$var reg 8 A B [7:0] $end
$var reg 24 B acc [23:0] $end
$var reg 1 C busy $end
$var reg 4 D count [3:0] $end
$var reg 1 , done $end
$var reg 24 E y [23:0] $end
$upscope $end
$upscope $end
$upscope $end
$enddefinitions $end
$comment Show the parameter values. $end
$dumpall
b1000 ?
b10000 >
b1000 3
b11 2
b10 1
b1 0
b0 /
b101 .
b100 -
$end
#0
$dumpvars
b0 E
b0 D
0C
b0 B
b0 A
b0 @
b0 =
b0 <
b0 ;
b0 :
09
b0 8
b0 7
b0 6
b0 5
b0 4
0,
b0 +
b0 *
b0 )
0(
1'
0&
b0 %
b0 $
0#
0"
b0 !
$end
#5000
1&
#10000
1(
b100 %
b100 *
b11 $
b11 )
0&
0'
#15000
b1 :
19
b100 8
b100 =
b11 <
b11 7
1#
1&
#20000
0(
0&
#25000
09
1C
b100 A
b11 @
1&
#30000
0&
#35000
b1 D
b10 A
b110 @
1&
#40000
0&
#45000
b10 D
b1 A
b1100 @
1&
#50000
0&
#55000
b11 D
b0 A
b11000 @
b1100 B
1&
#60000
0&
#65000
b100 D
b110000 @
1&
#70000
0&
#75000
b101 D
b1100000 @
1&
#80000
0&
#85000
b110 D
b11000000 @
1&
#90000
0&
#95000
b111 D
b110000000 @
1&
#100000
0&
#105000
0C
1,
b1100 +
b1100 E
b1000 D
b1100000000 @
1&
#110000
0&
#115000
0,
b10 :
19
b11 8
b11 =
b1100 6
1&
#120000
0&
#125000
09
1C
b0 D
b0 B
b11 A
b11 @
1&
#130000
0&
#135000
b1 D
b1 A
b110 @
b11 B
1&
#140000
0&
#145000
b10 D
b0 A
b1100 @
b1001 B
1&
#150000
0&
#155000
b11 D
b11000 @
1&
#160000
0&
#165000
b100 D
b110000 @
1&
#170000
0&
#175000
b101 D
b1100000 @
1&
#180000
0&
#185000
b110 D
b11000000 @
1&
#190000
0&
#195000
b111 D
b110000000 @
1&
#200000
0&
#205000
0C
1,
b1001 +
b1001 E
b1000 D
b1100000000 @
1&
#210000
0&
#215000
0,
b11 :
19
b1001 <
b1001 7
b1001 4
1&
#220000
0&
#225000
09
1C
b0 D
b0 B
b11 A
b1001 @
1&
#230000
0&
#235000
b1 D
b1 A
b10010 @
b1001 B
1&
#240000
0&
#245000
b10 D
b0 A
b100100 @
b11011 B
1&
#250000
0&
#255000
b11 D
b1001000 @
1&
#260000
0&
#265000
b100 D
b10010000 @
1&
#270000
0&
#275000
b101 D
b100100000 @
1&
#280000
0&
#285000
b110 D
b1001000000 @
1&
#290000
0&
#295000
b111 D
b10010000000 @
1&
#300000
0&
#305000
0C
1,
b11011 +
b11011 E
b1000 D
b100100000000 @
1&
#310000
0&
#315000
0,
b100 :
b11011 5
1&
#320000
0&
#325000
b101 :
b100111 !
b100111 ;
1&
#330000
0&
#335000
b0 :
0#
1"
1&
#340000
1(
b10 %
b10 *
b101 $
b101 )
0&
#345000
b1 :
19
b10 8
b10 =
b101 <
b101 7
1#
0"
1&
#350000
0(
0&
#355000
1C
b0 D
b0 B
b10 A
b101 @
09
1&
#360000
0&
#365000
b1 D
b1 A
b1010 @
1&
#370000
0&
#375000
b10 D
b0 A
b10100 @
b1010 B
1&
#380000
0&
#385000
b11 D
b101000 @
1&
#390000
0&
#395000
b100 D
b1010000 @
1&
#400000
0&
#405000
b101 D
b10100000 @
1&
#410000
0&
#415000
b110 D
b101000000 @
1&
#420000
0&
#425000
b111 D
b1010000000 @
1&
#430000
0&
#435000
0C
1,
b1010 +
b1010 E
b1000 D
b10100000000 @
1&
#440000
0&
#445000
b10 :
19
b101 8
b101 =
b1010 6
0,
1&
#450000
0&
#455000
1C
b0 D
b0 B
b101 A
b101 @
09
1&
#460000
0&
#465000
b1 D
b10 A
b1010 @
b101 B
1&
#470000
0&
#475000
b10 D
b1 A
b10100 @
1&
#480000
0&
#485000
b11 D
b0 A
b101000 @
b11001 B
1&
#490000
0&
#495000
b100 D
b1010000 @
1&
#500000
0&
#505000
b101 D
b10100000 @
1&
#510000
0&
#515000
b110 D
b101000000 @
1&
#520000
0&
#525000
b111 D
b1010000000 @
1&
#530000
0&
#535000
0C
1,
b11001 +
b11001 E
b1000 D
b10100000000 @
1&
#540000
0&
#545000
b11 :
19
b11001 <
b11001 7
b11001 4
0,
1&
#550000
0&
#555000
1C
b0 D
b0 B
b101 A
b11001 @
09
1&
#560000
0&
#565000
b1 D
b10 A
b110010 @
b11001 B
1&
#570000
0&
#575000
b10 D
b1 A
b1100100 @
1&
#580000
0&
#585000
b11 D
b0 A
b11001000 @
b1111101 B
1&
#590000
0&
#595000
b100 D
b110010000 @
1&
#600000
0&
#605000
b101 D
b1100100000 @
1&
#610000
0&
#615000
b110 D
b11001000000 @
1&
#620000
0&
#625000
b111 D
b110010000000 @
1&
#630000
0&
#635000
0C
1,
b1111101 +
b1111101 E
b1000 D
b1100100000000 @
1&
#640000
0&
#645000
b100 :
b1111101 5
0,
1&
#650000
0&
#655000
b101 :
b10000111 !
b10000111 ;
1&
#660000
0&
#665000
b0 :
0#
1"
1&
#670000
1(
b1010 %
b1010 *
b1010 $
b1010 )
0&
#675000
b1 :
19
b1010 8
b1010 =
b1010 <
b1010 7
1#
0"
1&
#680000
0(
0&
#685000
09
1C
b0 D
b0 B
b1010 A
b1010 @
1&
#690000
0&
#695000
b1 D
b101 A
b10100 @
1&
#700000
0&
#705000
b10 D
b10 A
b101000 @
b10100 B
1&
#710000
0&
#715000
b11 D
b1 A
b1010000 @
1&
#720000
0&
#725000
b100 D
b0 A
b10100000 @
b1100100 B
1&
#730000
0&
#735000
b101 D
b101000000 @
1&
#740000
0&
#745000
b110 D
b1010000000 @
1&
#750000
0&
#755000
b111 D
b10100000000 @
1&
#760000
0&
#765000
0C
1,
b1100100 +
b1100100 E
b1000 D
b101000000000 @
1&
#770000
0&
#775000
0,
b10 :
19
b1100100 6
1&
#780000
0&
#785000
09
1C
b0 D
b0 B
b1010 A
b1010 @
1&
#790000
0&
#795000
b1 D
b101 A
b10100 @
1&
#800000
0&
#805000
b10 D
b10 A
b101000 @
b10100 B
1&
#810000
0&
#815000
b11 D
b1 A
b1010000 @
1&
#820000
0&
#825000
b100 D
b0 A
b10100000 @
b1100100 B
1&
#830000
0&
#835000
b101 D
b101000000 @
1&
#840000
0&
#845000
b110 D
b1010000000 @
1&
#850000
0&
#855000
b111 D
b10100000000 @
1&
#860000
0&
#865000
0C
1,
b1000 D
b101000000000 @
1&
#870000
0&
#875000
0,
b11 :
19
b1100100 <
b1100100 7
b1100100 4
1&
#880000
0&
#885000
09
1C
b0 D
b0 B
b1010 A
b1100100 @
1&
#890000
0&
#895000
b1 D
b101 A
b11001000 @
1&
#900000
0&
#905000
b10 D
b10 A
b110010000 @
b11001000 B
1&
#910000
0&
#915000
b11 D
b1 A
b1100100000 @
1&
#920000
0&
#925000
b100 D
b0 A
b11001000000 @
b1111101000 B
1&
#930000
0&
#935000
b101 D
b110010000000 @
1&
#940000
0&
#945000
b110 D
b1100100000000 @
1&
#950000
0&
#955000
b111 D
b11001000000000 @
1&
#960000
0&
#965000
0C
1,
b1111101000 +
b1111101000 E
b1000 D
b110010000000000 @
1&
#970000
0&
#975000
0,
b100 :
b1111101000 5
1&
#980000
0&
#985000
b101 :
b10001001100 !
b10001001100 ;
1&
#990000
0&
#995000
b0 :
0#
1"
1&
#1000000
1(
b0 %
b0 *
b0 $
b0 )
0&
#1005000
b1 :
19
b0 8
b0 =
b0 <
b0 7
1#
0"
1&
#1010000
0(
0&
#1015000
1C
b0 D
b0 B
b0 @
09
1&
#1020000
0&
#1025000
b1 D
1&
#1030000
0&
#1035000
b10 D
1&
#1040000
0&
#1045000
b11 D
1&
#1050000
0&
#1055000
b100 D
1&
#1060000
0&
#1065000
b101 D
1&
#1070000
0&
#1075000
b110 D
1&
#1080000
0&
#1085000
b111 D
1&
#1090000
0&
#1095000
0C
1,
b0 +
b0 E
b1000 D
1&
#1100000
0&
#1105000
b10 :
19
b0 6
0,
1&
#1110000
0&
#1115000
1C
b0 D
09
1&
#1120000
0&
#1125000
b1 D
1&
#1130000
0&
#1135000
b10 D
1&
#1140000
0&
#1145000
b11 D
1&
#1150000
0&
#1155000
b100 D
1&
#1160000
0&
#1165000
b101 D
1&
#1170000
0&
#1175000
b110 D
1&
#1180000
0&
#1185000
b111 D
1&
#1190000
0&
#1195000
0C
1,
b1000 D
1&
#1200000
0&
#1205000
b11 :
19
b0 4
0,
1&
#1210000
0&
#1215000
1C
b0 D
09
1&
#1220000
0&
#1225000
b1 D
1&
#1230000
0&
#1235000
b10 D
1&
#1240000
0&
#1245000
b11 D
1&
#1250000
0&
#1255000
b100 D
1&
#1260000
0&
#1265000
b101 D
1&
#1270000
0&
#1275000
b110 D
1&
#1280000
0&
#1285000
b111 D
1&
#1290000
0&
#1295000
0C
1,
b1000 D
1&
#1300000
0&
#1305000
b100 :
b0 5
0,
1&
#1310000
0&
#1315000
b101 :
b0 !
b0 ;
1&
#1320000
0&
#1325000
b0 :
0#
1"
1&
#1330000
1(
b101 %
b101 *
b1 $
b1 )
0&
#1335000
b1 :
19
b101 8
b101 =
b1 <
b1 7
1#
0"
1&
#1340000
0(
0&
#1345000
09
1C
b0 D
b101 A
b1 @
1&
#1350000
0&
#1355000
b1 D
b10 A
b10 @
b1 B
1&
#1360000
0&
#1365000
b10 D
b1 A
b100 @
1&
#1370000
0&
#1375000
b11 D
b0 A
b1000 @
b101 B
1&
#1380000
0&
#1385000
b100 D
b10000 @
1&
#1390000
0&
#1395000
b101 D
b100000 @
1&
#1400000
0&
#1405000
b110 D
b1000000 @
1&
#1410000
0&
#1415000
b111 D
b10000000 @
1&
#1420000
0&
#1425000
0C
1,
b101 +
b101 E
b1000 D
b100000000 @
1&
#1430000
0&
#1435000
0,
b10 :
19
b1 8
b1 =
b101 6
1&
#1440000
0&
#1445000
09
1C
b0 D
b0 B
b1 A
b1 @
1&
#1450000
0&
#1455000
b1 D
b0 A
b10 @
b1 B
1&
#1460000
0&
#1465000
b10 D
b100 @
1&
#1470000
0&
#1475000
b11 D
b1000 @
1&
#1480000
0&
#1485000
b100 D
b10000 @
1&
#1490000
0&
#1495000
b101 D
b100000 @
1&
#1500000
0&
#1505000
b110 D
b1000000 @
1&
#1510000
0&
#1515000
b111 D
b10000000 @
1&
#1520000
0&
#1525000
0C
1,
b1 +
b1 E
b1000 D
b100000000 @
1&
#1530000
0&
#1535000
0,
b11 :
19
b1 4
1&
#1540000
0&
#1545000
09
1C
b0 D
b0 B
b1 A
b1 @
1&
#1550000
0&
#1555000
b1 D
b0 A
b10 @
b1 B
1&
#1560000
0&
#1565000
b10 D
b100 @
1&
#1570000
0&
#1575000
b11 D
b1000 @
1&
#1580000
0&
#1585000
b100 D
b10000 @
1&
#1590000
0&
#1595000
b101 D
b100000 @
1&
#1600000
0&
#1605000
b110 D
b1000000 @
1&
#1610000
0&
#1615000
b111 D
b10000000 @
1&
#1620000
0&
#1625000
0C
1,
b1000 D
b100000000 @
1&
#1630000
0&
#1635000
0,
b100 :
b1 5
1&
#1640000
0&
#1645000
b101 :
b110 !
b110 ;
1&
#1650000
0&
#1655000
b0 :
0#
1"
1&
#1660000
1(
b111 %
b111 *
b10 $
b10 )
0&
#1665000
b1 :
19
b111 8
b111 =
b10 <
b10 7
1#
0"
1&
#1670000
0(
0&
#1675000
1C
b0 D
b0 B
b111 A
b10 @
09
1&
#1680000
0&
#1685000
b1 D
b11 A
b100 @
b10 B
1&
#1690000
0&
#1695000
b10 D
b1 A
b1000 @
b110 B
1&
#1700000
0&
#1705000
b11 D
b0 A
b10000 @
b1110 B
1&
#1710000
0&
#1715000
b100 D
b100000 @
1&
#1720000
0&
#1725000
b101 D
b1000000 @
1&
#1730000
0&
#1735000
b110 D
b10000000 @
1&
#1740000
0&
#1745000
b111 D
b100000000 @
1&
#1750000
0&
#1755000
0C
1,
b1110 +
b1110 E
b1000 D
b1000000000 @
1&
#1760000
0&
#1765000
b10 :
19
b10 8
b10 =
b1110 6
0,
1&
#1770000
0&
#1775000
1C
b0 D
b0 B
b10 A
b10 @
09
1&
#1780000
0&
#1785000
b1 D
b1 A
b100 @
1&
#1790000
0&
#1795000
b10 D
b0 A
b1000 @
b100 B
1&
#1800000
0&
#1805000
b11 D
b10000 @
1&
#1810000
0&
#1815000
b100 D
b100000 @
1&
#1820000
0&
#1825000
b101 D
b1000000 @
1&
#1830000
0&
#1835000
b110 D
b10000000 @
1&
#1840000
0&
#1845000
b111 D
b100000000 @
1&
#1850000
0&
#1855000
0C
1,
b100 +
b100 E
b1000 D
b1000000000 @
1&
#1860000
0&
#1865000
b11 :
19
b100 <
b100 7
b100 4
0,
1&
#1870000
0&
#1875000
1C
b0 D
b0 B
b10 A
b100 @
09
1&
#1880000
0&
#1885000
b1 D
b1 A
b1000 @
1&
#1890000
0&
#1895000
b10 D
b0 A
b10000 @
b1000 B
1&
#1900000
0&
#1905000
b11 D
b100000 @
1&
#1910000
0&
#1915000
b100 D
b1000000 @
1&
#1920000
0&
#1925000
b101 D
b10000000 @
1&
#1930000
0&
#1935000
b110 D
b100000000 @
1&
#1940000
0&
#1945000
b111 D
b1000000000 @
1&
#1950000
0&
#1955000
0C
1,
b1000 +
b1000 E
b1000 D
b10000000000 @
1&
#1960000
0&
#1965000
b100 :
b1000 5
0,
1&
#1970000
0&
#1975000
b101 :
b10110 !
b10110 ;
1&
#1980000
0&
#1985000
b0 :
0#
1"
1&
#1990000
1(
b11 %
b11 *
b100 $
b100 )
0&
#1995000
b1 :
19
b11 8
b11 =
1#
0"
1&
#2000000
0(
0&
#2005000
09
1C
b0 D
b0 B
b11 A
b100 @
1&
#2010000
0&
#2015000
b1 D
b1 A
b1000 @
b100 B
1&
#2020000
0&
#2025000
b10 D
b0 A
b10000 @
b1100 B
1&
#2030000
0&
#2035000
b11 D
b100000 @
1&
#2040000
0&
#2045000
b100 D
b1000000 @
1&
#2050000
0&
#2055000
b101 D
b10000000 @
1&
#2060000
0&
#2065000
b110 D
b100000000 @
1&
#2070000
0&
#2075000
b111 D
b1000000000 @
1&
#2080000
0&
#2085000
0C
1,
b1100 +
b1100 E
b1000 D
b10000000000 @
1&
#2090000
0&
#2095000
0,
b10 :
19
b100 8
b100 =
b1100 6
1&
#2100000
0&
#2105000
09
1C
b0 D
b0 B
b100 A
b100 @
1&
#2110000
0&
#2115000
b1 D
b10 A
b1000 @
1&
#2120000
0&
#2125000
b10 D
b1 A
b10000 @
1&
#2130000
0&
#2135000
b11 D
b0 A
b100000 @
b10000 B
1&
#2140000
0&
#2145000
b100 D
b1000000 @
1&
#2150000
0&
#2155000
b101 D
b10000000 @
1&
#2160000
0&
#2165000
b110 D
b100000000 @
1&
#2170000
0&
#2175000
b111 D
b1000000000 @
1&
#2180000
0&
#2185000
0C
1,
b10000 +
b10000 E
b1000 D
b10000000000 @
1&
#2190000
0&
#2195000
0,
b11 :
19
b10000 <
b10000 7
b10000 4
1&
#2200000
0&
#2205000
09
1C
b0 D
b0 B
b100 A
b10000 @
1&
#2210000
0&
#2215000
b1 D
b10 A
b100000 @
1&
#2220000
0&
#2225000
b10 D
b1 A
b1000000 @
1&
#2230000
0&
#2235000
b11 D
b0 A
b10000000 @
b1000000 B
1&
#2240000
0&
#2245000
b100 D
b100000000 @
1&
#2250000
0&
#2255000
b101 D
b1000000000 @
1&
#2260000
0&
#2265000
b110 D
b10000000000 @
1&
#2270000
0&
#2275000
b111 D
b100000000000 @
1&
#2280000
0&
#2285000
0C
1,
b1000000 +
b1000000 E
b1000 D
b1000000000000 @
1&
#2290000
0&
#2295000
0,
b100 :
b1000000 5
1&
#2300000
0&
#2305000
b101 :
b1001100 !
b1001100 ;
1&
#2310000
0&
#2315000
b0 :
0#
1"
1&
#2320000
1(
b1 %
b1 *
b1000 $
b1000 )
0&
#2325000
b1 :
19
b1 8
b1 =
b1000 <
b1000 7
1#
0"
1&
#2330000
0(
0&
#2335000
1C
b0 D
b0 B
b1 A
b1000 @
09
1&
#2340000
0&
#2345000
b1 D
b0 A
b10000 @
b1000 B
1&
#2350000
0&
#2355000
b10 D
b100000 @
1&
#2360000
0&
#2365000
b11 D
b1000000 @
1&
#2370000
0&
#2375000
b100 D
b10000000 @
1&
#2380000
0&
#2385000
b101 D
b100000000 @
1&
#2390000
0&
#2395000
b110 D
b1000000000 @
1&
#2400000
0&
#2405000
b111 D
b10000000000 @
1&
#2410000
0&
#2415000
0C
1,
b1000 +
b1000 E
b1000 D
b100000000000 @
1&
#2420000
0&
#2425000
b10 :
19
b1000 8
b1000 =
b1000 6
0,
1&
#2430000
0&
#2435000
1C
b0 D
b0 B
b1000 A
b1000 @
09
1&
#2440000
0&
#2445000
b1 D
b100 A
b10000 @
1&
#2450000
0&
#2455000
b10 D
b10 A
b100000 @
1&
#2460000
0&
#2465000
b11 D
b1 A
b1000000 @
1&
#2470000
0&
#2475000
b100 D
b0 A
b10000000 @
b1000000 B
1&
#2480000
0&
#2485000
b101 D
b100000000 @
1&
#2490000
0&
#2495000
b110 D
b1000000000 @
1&
#2500000
0&
#2505000
b111 D
b10000000000 @
1&
#2510000
0&
#2515000
0C
1,
b1000000 +
b1000000 E
b1000 D
b100000000000 @
1&
#2520000
0&
#2525000
b11 :
19
b1000000 <
b1000000 7
b1000000 4
0,
1&
#2530000
0&
#2535000
1C
b0 D
b0 B
b1000 A
b1000000 @
09
1&
#2540000
0&
#2545000
b1 D
b100 A
b10000000 @
1&
#2550000
0&
#2555000
b10 D
b10 A
b100000000 @
1&
#2560000
0&
#2565000
b11 D
b1 A
b1000000000 @
1&
#2570000
0&
#2575000
b100 D
b0 A
b10000000000 @
b1000000000 B
1&
#2580000
0&
#2585000
b101 D
b100000000000 @
1&
#2590000
0&
#2595000
b110 D
b1000000000000 @
1&
#2600000
0&
#2605000
b111 D
b10000000000000 @
1&
#2610000
0&
#2615000
0C
1,
b1000000000 +
b1000000000 E
b1000 D
b100000000000000 @
1&
#2620000
0&
#2625000
b100 :
b1000000000 5
0,
1&
#2630000
0&
#2635000
b101 :
b1000001000 !
b1000001000 ;
1&
#2640000
0&
#2645000
b0 :
0#
1"
1&
#2650000
1(
b0 %
b0 *
b1010 $
b1010 )
0&
#2655000
b1 :
19
b0 8
b0 =
b1010 <
b1010 7
1#
0"
1&
#2660000
0(
0&
#2665000
09
1C
b0 D
b0 B
b1010 @
1&
#2670000
0&
#2675000
b1 D
b10100 @
1&
#2680000
0&
#2685000
b10 D
b101000 @
1&
#2690000
0&
#2695000
b11 D
b1010000 @
1&
#2700000
0&
#2705000
b100 D
b10100000 @
1&
#2710000
0&
#2715000
b101 D
b101000000 @
1&
#2720000
0&
#2725000
b110 D
b1010000000 @
1&
#2730000
0&
#2735000
b111 D
b10100000000 @
1&
#2740000
0&
#2745000
0C
1,
b0 +
b0 E
b1000 D
b101000000000 @
1&
#2750000
0&
#2755000
0,
b10 :
19
b1010 8
b1010 =
b0 6
1&
#2760000
0&
#2765000
09
1C
b0 D
b1010 A
b1010 @
1&
#2770000
0&
#2775000
b1 D
b101 A
b10100 @
1&
#2780000
0&
#2785000
b10 D
b10 A
b101000 @
b10100 B
1&
#2790000
0&
#2795000
b11 D
b1 A
b1010000 @
1&
#2800000
0&
#2805000
b100 D
b0 A
b10100000 @
b1100100 B
1&
#2810000
0&
#2815000
b101 D
b101000000 @
1&
#2820000
0&
#2825000
b110 D
b1010000000 @
1&
#2830000
0&
#2835000
b111 D
b10100000000 @
1&
#2840000
0&
#2845000
0C
1,
b1100100 +
b1100100 E
b1000 D
b101000000000 @
1&
#2850000
0&
#2855000
0,
b11 :
19
b1100100 <
b1100100 7
b1100100 4
1&
#2860000
0&
#2865000
09
1C
b0 D
b0 B
b1010 A
b1100100 @
1&
#2870000
0&
#2875000
b1 D
b101 A
b11001000 @
1&
#2880000
0&
#2885000
b10 D
b10 A
b110010000 @
b11001000 B
1&
#2890000
0&
#2895000
b11 D
b1 A
b1100100000 @
1&
#2900000
0&
#2905000
b100 D
b0 A
b11001000000 @
b1111101000 B
1&
#2910000
0&
#2915000
b101 D
b110010000000 @
1&
#2920000
0&
#2925000
b110 D
b1100100000000 @
1&
#2930000
0&
#2935000
b111 D
b11001000000000 @
1&
#2940000
0&
#2945000
0C
1,
b1111101000 +
b1111101000 E
b1000 D
b110010000000000 @
1&
#2950000
0&
#2955000
0,
b100 :
b1111101000 5
1&
#2960000
0&
#2965000
b101 :
b1111101000 !
b1111101000 ;
1&
#2970000
0&
#2975000
b0 :
0#
1"
1&
#2980000
1(
b1111 %
b1111 *
b1111 $
b1111 )
0&
#2985000
b1 :
19
b1111 8
b1111 =
b1111 <
b1111 7
1#
0"
1&
#2990000
0(
0&
#2995000
1C
b0 D
b0 B
b1111 A
b1111 @
09
1&
#3000000
0&
#3005000
b1 D
b111 A
b11110 @
b1111 B
1&
#3010000
0&
#3015000
b10 D
b11 A
b111100 @
b101101 B
1&
#3020000
0&
#3025000
b11 D
b1 A
b1111000 @
b1101001 B
1&
#3030000
0&
#3035000
b100 D
b0 A
b11110000 @
b11100001 B
1&
#3040000
0&
#3045000
b101 D
b111100000 @
1&
#3050000
0&
#3055000
b110 D
b1111000000 @
1&
#3060000
0&
#3065000
b111 D
b11110000000 @
1&
#3070000
0&
#3075000
0C
1,
b11100001 +
b11100001 E
b1000 D
b111100000000 @
1&
#3080000
0&
#3085000
b10 :
19
b11100001 6
0,
1&
#3090000
0&
#3095000
1C
b0 D
b0 B
b1111 A
b1111 @
09
1&
#3100000
0&
#3105000
b1 D
b111 A
b11110 @
b1111 B
1&
#3110000
0&
#3115000
b10 D
b11 A
b111100 @
b101101 B
1&
#3120000
0&
#3125000
b11 D
b1 A
b1111000 @
b1101001 B
1&
#3130000
0&
#3135000
b100 D
b0 A
b11110000 @
b11100001 B
1&
#3140000
0&
#3145000
b101 D
b111100000 @
1&
#3150000
0&
#3155000
b110 D
b1111000000 @
1&
#3160000
0&
#3165000
b111 D
b11110000000 @
1&
#3170000
0&
#3175000
0C
1,
b1000 D
b111100000000 @
1&
#3180000
0&
#3185000
b11 :
19
b11100001 <
b11100001 7
b11100001 4
0,
1&
#3190000
0&
#3195000
1C
b0 D
b0 B
b1111 A
b11100001 @
09
1&
#3200000
0&
#3205000
b1 D
b111 A
b111000010 @
b11100001 B
1&
#3210000
0&
#3215000
b10 D
b11 A
b1110000100 @
b1010100011 B
1&
#3220000
0&
